bytehub/__init__.py
bytehub/cli.py
bytehub/manager.py
bytehub/scaffold.py
bytehub_discord_multitool-0.1.0.dist-info/licenses/LICENSE
bytehub_discord_multitool-0.1.0.dist-info/METADATA
bytehub_discord_multitool-0.1.0.dist-info/WHEEL
bytehub_discord_multitool-0.1.0.dist-info/entry_points.txt
bytehub_discord_multitool-0.1.0.dist-info/top_level.txt
bytehub_discord_multitool-0.1.0.dist-info/RECORD
