Metadata-Version: 2.4
Name: bytehub-discord-multitool
Version: 0.1.0
Summary: ByteHub Discord MultiTool
Author: ByteHub
License: MIT
Requires-Python: >=3.11
License-File: LICENSE
Requires-Dist: typer[all]==0.9.0
Requires-Dist: click==8.1.7
Requires-Dist: discord.py==2.6.4
Requires-Dist: fastapi==0.95.0
Requires-Dist: uvicorn[standard]==0.22.0
Requires-Dist: python-dotenv==1.0.0
Requires-Dist: psutil==5.9.0
Requires-Dist: pydantic==1.10.12
Requires-Dist: httpx==0.24.0
Requires-Dist: cryptography==41.0.0
Dynamic: license-file
